kubeSetup/__init__.py
kubeSetup/__main__.py
kubeSetup/cli.py
kubeSetup/commands/__init__.py
kubeSetup/commands/_cluster_cleanup.py
kubeSetup/commands/_complexCluster.py
kubeSetup/commands/_simpleCluster.py
kubeSetup/commands/utils/__init__.py
kubeSetup/commands/utils/_clusterSetup/__init__.py
kubeSetup/commands/utils/_clusterSetup/_schemas.py
kubeSetup/commands/utils/_clusterSetup/_setup.py
kubeSetup/commands/utils/_clusterSetup/templates/complex/calico.j2
kubeSetup/commands/utils/_clusterSetup/templates/complex/calico.yaml
kubeSetup/commands/utils/_clusterSetup/templates/complex/kubeadm-config.j2
kubeSetup/commands/utils/_clusterSetup/templates/simple/calico.j2
kubeSetup/commands/utils/_clusterSetup/templates/simple/calico.yaml
kubeSetup/commands/utils/_clusterSetup/templates/simple/kubeadm-config.j2
kubeSetup/commands/utils/_complexCluster/__init__.py
kubeSetup/commands/utils/_complexCluster/_haproxy_setup.py
kubeSetup/commands/utils/_complexCluster/_keepalive_setup.py
kubeSetup/commands/utils/_complexCluster/_templates/check_apiserver-template.j2
kubeSetup/commands/utils/_complexCluster/_templates/haproxy-conf.j2
kubeSetup/commands/utils/_complexCluster/_templates/keepalived-conf.j2
kubeSetup/commands/utils/_proxmox/__init__.py
kubeSetup/commands/utils/_proxmox/_proxmox.py
kubeSetup/commands/utils/_setup/__init__.py
kubeSetup/commands/utils/_setup/_proxmox_conf.py
kubeSetup/commands/utils/_setup/_schemas.py
kubeSetup/commands/utils/_setup/_utils.py
kubeSetup/commands/utils/_setup/_vm_cleanup_conf.py
kubeSetup/commands/utils/_setup/_vm_complex_conf.py
kubeSetup/commands/utils/_setup/_vm_simple_conf.py
kubeSetup/commands/utils/_setup/tests/test_proxmox_conf.py
kubeSetup/commands/utils/_setup/tests/test_vm_conf.py
kubeSetup/commands/utils/_setupUtils/__init__.py
kubeSetup/commands/utils/_setupUtils/_general_commands.py
kubeSetup/commands/utils/_setupUtils/_logging.py
kubeSetup/commands/utils/_setupUtils/_preconf.py
k8s_proxmox_cluster-0.1.73.dist-info/METADATA
k8s_proxmox_cluster-0.1.73.dist-info/WHEEL
k8s_proxmox_cluster-0.1.73.dist-info/RECORD
