Metadata-Version: 2.1
Name: k8s-proxmox-cluster
Version: 0.1.73
Summary: A cli to install simple and complex kubernetese cluster
License: MIT
Author: mueth
Author-email: muethom@icloud.com
Requires-Python: >=3.12,<4.0
Classifier: License :: OSI Approved :: MIT License
Classifier: Programming Language :: Python :: 3
Classifier: Programming Language :: Python :: 3.12
Classifier: Programming Language :: Python :: 3.13
Requires-Dist: Jinja2 (>=3.1.4,<4.0.0)
Requires-Dist: black (>=24.10.0,<25.0.0)
Requires-Dist: click (>=8.1.7,<9.0.0)
Requires-Dist: colorama (>=0.4.6,<0.5.0)
Requires-Dist: paramiko (>=3.5.0,<4.0.0)
Requires-Dist: proxmoxer (>=2.1.0,<3.0.0)
Requires-Dist: requests (>=2.32.3,<3.0.0)
Requires-Dist: tqdm (>=4.67.1,<5.0.0)
Requires-Dist: types-colorama (>=0.4.15.20240311,<0.5.0.0)
Requires-Dist: types-paramiko (>=3.5.0.20240928,<4.0.0.0)
Requires-Dist: types-tqdm (>=4.67.0.20241119,<5.0.0.0)
